

{
    "version": "1.0.0",
    "items": [
    {
        "name":"test",
        "href":"https://m.baidu.com",
        "favicon":"https://m.baidu.com/favicon.ico",
        "external":"./external.js",
        "vuex":"./storage/vuex",
        "iStarted":false,
        "iDestoryed":false,
        "iMinimized":false,
        "iActived":false
    },
    {
        "name":"RemoteController",
        "href":"http://localhost:8081",
        "favicon":"./favicon.ico",
        "external":"./external.js",
        "vuex":"./storage/vuex",
        "iStarted":false,
        "iDestoryed":false,
        "iMinimized":false,
        "iActived":false
    }
]
}